fastapi_aws_lambda/__init__.py
fastapi_aws_lambda/config.py
fastapi_aws_lambda/db.py
fastapi_aws_lambda/main.py
tests/__init__.py
fastapi_aws_lambda-0.0.1.dist-info/METADATA
fastapi_aws_lambda-0.0.1.dist-info/WHEEL
fastapi_aws_lambda-0.0.1.dist-info/top_level.txt
fastapi_aws_lambda-0.0.1.dist-info/RECORD
