Metadata-Version: 2.1
Name: fastapi-aws-lambda
Version: 0.0.1
Summary: A Wrapper for FastAPI to run on AWS Lambda
Home-page: https://github.com/obahamonde/fastapi_lambda
Author: Oscar Bahamonde
Author-email: oscar.bahamonde@hatarini.com
License: MIT
Classifier: Development Status :: 3 - Alpha
Classifier: Intended Audience :: Developers
Classifier: License :: OSI Approved :: MIT License
Classifier: Programming Language :: Python :: 3.7
Classifier: Programming Language :: Python :: 3.8
Classifier: Programming Language :: Python :: 3.9
Requires-Dist: fastapi
Requires-Dist: odmantic
Requires-Dist: pydantic[dotenv,email]
Requires-Dist: python-multipart
Requires-Dist: python-jose
Requires-Dist: mangum
